{
  "ffbe20aec8a29ba6eaa7022038aaec88": {
    "min_num": 0,
    "min_loss": 2.902158498764038,
    "best_config": {
      "learning_rate": 0.004,
      "weight_decay": 0.1,
      "min_lr_ratio": 0,
      "warmup": 4000,
      "beta1": 0.98,
      "beta2": 0.98,
      "epsilon": 1e-10,
      "max_grad_norm": 1,
      "nesterov": true,
      "train_batch_size": 256
    },
    "approximate_best_config_list": [
      {
        "learning_rate": 0.004,
        "weight_decay": 0.1,
        "min_lr_ratio": 0,
        "warmup": 4000,
        "beta1": 0.98,
        "beta2": 0.98,
        "epsilon": 1e-10,
        "max_grad_norm": 1,
        "nesterov": true,
        "train_batch_size": 256
      }
    ]
  },
  "8605541c78025b39ff58dd75a779cb84": {
    "min_num": 0,
    "min_loss": 2.8329575061798096,
    "best_config": {
      "learning_rate": 0.004,
      "weight_decay": 0.1,
      "min_lr_ratio": 0,
      "warmup": 4000,
      "beta1": 0.98,
      "beta2": 0.98,
      "epsilon": 1e-10,
      "max_grad_norm": 1,
      "nesterov": true,
      "train_batch_size": 256
    },
    "approximate_best_config_list": [
      {
        "learning_rate": 0.004,
        "weight_decay": 0.1,
        "min_lr_ratio": 0,
        "warmup": 4000,
        "beta1": 0.98,
        "beta2": 0.98,
        "epsilon": 1e-10,
        "max_grad_norm": 1,
        "nesterov": true,
        "train_batch_size": 256
      }
    ]
  },
  "a22920dcb14e8a434321dd042b0fd02d": {
    "min_num": 0,
    "min_loss": 2.784677267074585,
    "best_config": {
      "learning_rate": 0.004,
      "weight_decay": 0.1,
      "min_lr_ratio": 0,
      "warmup": 4000,
      "beta1": 0.98,
      "beta2": 0.98,
      "epsilon": 1e-10,
      "max_grad_norm": 1,
      "nesterov": true,
      "train_batch_size": 256
    },
    "approximate_best_config_list": [
      {
        "learning_rate": 0.004,
        "weight_decay": 0.1,
        "min_lr_ratio": 0,
        "warmup": 4000,
        "beta1": 0.98,
        "beta2": 0.98,
        "epsilon": 1e-10,
        "max_grad_norm": 1,
        "nesterov": true,
        "train_batch_size": 256
      }
    ]
  },
  "f2a6691cf4c0e2231caf58318800ddb1": {
    "min_num": 0,
    "min_loss": 2.7485225200653076,
    "best_config": {
      "learning_rate": 0.004,
      "weight_decay": 0.1,
      "min_lr_ratio": 0,
      "warmup": 4000,
      "beta1": 0.98,
      "beta2": 0.98,
      "epsilon": 1e-10,
      "max_grad_norm": 1,
      "nesterov": true,
      "train_batch_size": 256
    },
    "approximate_best_config_list": [
      {
        "learning_rate": 0.004,
        "weight_decay": 0.1,
        "min_lr_ratio": 0,
        "warmup": 4000,
        "beta1": 0.98,
        "beta2": 0.98,
        "epsilon": 1e-10,
        "max_grad_norm": 1,
        "nesterov": true,
        "train_batch_size": 256
      }
    ]
  },
  "b74e050ac7fc3990dd567a853f94f0c8": {
    "min_num": 0,
    "min_loss": 2.904270648956299,
    "best_config": {
      "learning_rate": 0.002,
      "weight_decay": 0.2,
      "min_lr_ratio": 0,
      "warmup": 1000,
      "beta1": 0.9,
      "beta2": 0.98,
      "epsilon": 9.999999999999999e-26,
      "max_grad_norm": 2,
      "nesterov": 0,
      "train_batch_size": 256
    },
    "approximate_best_config_list": [
      {
        "learning_rate": 0.002,
        "weight_decay": 0.2,
        "min_lr_ratio": 0,
        "warmup": 1000,
        "beta1": 0.9,
        "beta2": 0.98,
        "epsilon": 9.999999999999999e-26,
        "max_grad_norm": 2,
        "nesterov": 0,
        "train_batch_size": 256
      },
      {
        "learning_rate": 0.002,
        "weight_decay": 0.2,
        "min_lr_ratio": 0,
        "warmup": 2000,
        "beta1": 0.9,
        "beta2": 0.98,
        "epsilon": 1e-10,
        "max_grad_norm": 2,
        "nesterov": 0,
        "train_batch_size": 256
      },
      {
        "learning_rate": 0.002,
        "weight_decay": 0.2,
        "min_lr_ratio": 0,
        "warmup": 2000,
        "beta1": 0.9,
        "beta2": 0.98,
        "epsilon": 1e-10,
        "max_grad_norm": 0,
        "nesterov": 0,
        "train_batch_size": 256
      },
      {
        "learning_rate": 0.002,
        "weight_decay": 0.2,
        "min_lr_ratio": 0,
        "warmup": 2000,
        "beta1": 0.9,
        "beta2": 0.98,
        "epsilon": 1e-15,
        "max_grad_norm": 2,
        "nesterov": 0,
        "train_batch_size": 256
      },
      {
        "learning_rate": 0.002,
        "weight_decay": 0.2,
        "min_lr_ratio": 0,
        "warmup": 2000,
        "beta1": 0.9,
        "beta2": 0.98,
        "epsilon": 9.999999999999999e-26,
        "max_grad_norm": 2,
        "nesterov": 0,
        "train_batch_size": 256
      },
      {
        "learning_rate": 0.002,
        "weight_decay": 0.2,
        "min_lr_ratio": 0,
        "warmup": 2000,
        "beta1": 0.9,
        "beta2": 0.98,
        "epsilon": 1e-20,
        "max_grad_norm": 2,
        "nesterov": 0,
        "train_batch_size": 256
      },
      {
        "learning_rate": 0.002,
        "weight_decay": 0.2,
        "min_lr_ratio": 0,
        "warmup": 2000,
        "beta1": 0.9,
        "beta2": 0.98,
        "epsilon": 1e-10,
        "max_grad_norm": 1,
        "nesterov": 0,
        "train_batch_size": 256
      },
      {
        "learning_rate": 0.002,
        "weight_decay": 0.2,
        "min_lr_ratio": 0,
        "warmup": 2000,
        "beta1": 0.95,
        "beta2": 0.98,
        "epsilon": 1e-10,
        "max_grad_norm": 2,
        "nesterov": 0,
        "train_batch_size": 256
      },
      {
        "learning_rate": 0.002,
        "weight_decay": 0.2,
        "min_lr_ratio": 0,
        "warmup": 2000,
        "beta1": 0.9,
        "beta2": 0.98,
        "epsilon": 1e-10,
        "max_grad_norm": 2,
        "nesterov": 0,
        "train_batch_size": 128
      }
    ]
  },
  "70b2eeb6de79e4b66e0cd7f9da73b3db": {
    "min_num": 0,
    "min_loss": 2.835987091064453,
    "best_config": {
      "learning_rate": 0.002,
      "weight_decay": 0.2,
      "min_lr_ratio": 0,
      "warmup": 1000,
      "beta1": 0.9,
      "beta2": 0.98,
      "epsilon": 1e-10,
      "max_grad_norm": 1,
      "nesterov": false,
      "train_batch_size": 256
    },
    "approximate_best_config_list": [
      {
        "learning_rate": 0.002,
        "weight_decay": 0.2,
        "min_lr_ratio": 0,
        "warmup": 1000,
        "beta1": 0.9,
        "beta2": 0.98,
        "epsilon": 1e-10,
        "max_grad_norm": 1,
        "nesterov": false,
        "train_batch_size": 256
      }
    ]
  },
  "197353b89fab039487bf9320bf702106": {
    "min_num": 0,
    "min_loss": 2.7871193885803223,
    "best_config": {
      "learning_rate": 0.002,
      "weight_decay": 0.2,
      "min_lr_ratio": 0,
      "warmup": 1000,
      "beta1": 0.9,
      "beta2": 0.98,
      "epsilon": 1e-10,
      "max_grad_norm": 1,
      "nesterov": false,
      "train_batch_size": 256
    },
    "approximate_best_config_list": [
      {
        "learning_rate": 0.002,
        "weight_decay": 0.2,
        "min_lr_ratio": 0,
        "warmup": 1000,
        "beta1": 0.9,
        "beta2": 0.98,
        "epsilon": 1e-10,
        "max_grad_norm": 1,
        "nesterov": false,
        "train_batch_size": 256
      }
    ]
  },
  "28f860282e91ceda94efeb3a597cfb90": {
    "min_num": 0,
    "min_loss": 2.752276659011841,
    "best_config": {
      "learning_rate": 0.002,
      "weight_decay": 0.2,
      "min_lr_ratio": 0,
      "warmup": 1000,
      "beta1": 0.9,
      "beta2": 0.98,
      "epsilon": 1e-10,
      "max_grad_norm": 1,
      "nesterov": false,
      "train_batch_size": 256
    },
    "approximate_best_config_list": [
      {
        "learning_rate": 0.002,
        "weight_decay": 0.2,
        "min_lr_ratio": 0,
        "warmup": 1000,
        "beta1": 0.9,
        "beta2": 0.98,
        "epsilon": 1e-10,
        "max_grad_norm": 1,
        "nesterov": false,
        "train_batch_size": 256
      }
    ]
  },
  "fecf4bb81df5690c2f84a2a992f9d2bc": {
    "min_num": 0,
    "min_loss": 2.8914880752563477,
    "best_config": {
      "learning_rate": 0.004,
      "weight_decay": 0.1,
      "min_lr_ratio": 0,
      "warmup": 0,
      "momentum": 0.98,
      "beta1": 0.8,
      "beta2": 0.98,
      "epsilon": 1e-15,
      "muon_epsilon": 1e-05,
      "max_grad_norm": 2,
      "lr_schedule": "linear",
      "muon_to_adam_lr": 0.3,
      "decay": 1,
      "train_batch_size": 256
    },
    "approximate_best_config_list": [
      {
        "learning_rate": 0.004,
        "weight_decay": 0.1,
        "min_lr_ratio": 0,
        "warmup": 0,
        "momentum": 0.98,
        "beta1": 0.8,
        "beta2": 0.98,
        "epsilon": 1e-15,
        "muon_epsilon": 1e-05,
        "max_grad_norm": 2,
        "lr_schedule": "linear",
        "muon_to_adam_lr": 0.3,
        "decay": 1,
        "train_batch_size": 256
      }
    ]
  },
  "64d0889cfda4f00683f3f74d8e6161f6": {
    "min_num": 0,
    "min_loss": 2.827101230621338,
    "best_config": {
      "learning_rate": 0.004,
      "weight_decay": 0.1,
      "min_lr_ratio": 0,
      "warmup": 0,
      "momentum": 0.98,
      "beta1": 0.8,
      "beta2": 0.98,
      "epsilon": 1e-15,
      "muon_epsilon": 1e-05,
      "max_grad_norm": 2,
      "lr_schedule": "linear",
      "muon_to_adam_lr": 0.3,
      "decay": 1,
      "train_batch_size": 256
    },
    "approximate_best_config_list": [
      {
        "learning_rate": 0.004,
        "weight_decay": 0.1,
        "min_lr_ratio": 0,
        "warmup": 0,
        "momentum": 0.98,
        "beta1": 0.8,
        "beta2": 0.98,
        "epsilon": 1e-15,
        "muon_epsilon": 1e-05,
        "max_grad_norm": 2,
        "lr_schedule": "linear",
        "muon_to_adam_lr": 0.3,
        "decay": 1,
        "train_batch_size": 256
      }
    ]
  },
  "09a3bc2eea575644ddd4c44cf473ecb6": {
    "min_num": 0,
    "min_loss": 2.7799859046936035,
    "best_config": {
      "learning_rate": 0.004,
      "weight_decay": 0.1,
      "min_lr_ratio": 0,
      "warmup": 0,
      "momentum": 0.98,
      "beta1": 0.8,
      "beta2": 0.98,
      "epsilon": 1e-15,
      "muon_epsilon": 1e-05,
      "max_grad_norm": 2,
      "lr_schedule": "linear",
      "muon_to_adam_lr": 0.3,
      "decay": 1,
      "train_batch_size": 256
    },
    "approximate_best_config_list": [
      {
        "learning_rate": 0.004,
        "weight_decay": 0.1,
        "min_lr_ratio": 0,
        "warmup": 0,
        "momentum": 0.98,
        "beta1": 0.8,
        "beta2": 0.98,
        "epsilon": 1e-15,
        "muon_epsilon": 1e-05,
        "max_grad_norm": 2,
        "lr_schedule": "linear",
        "muon_to_adam_lr": 0.3,
        "decay": 1,
        "train_batch_size": 256
      }
    ]
  },
  "8587c215fd52e1e657e1db7ff5d941aa": {
    "min_num": 0,
    "min_loss": 2.7483625411987305,
    "best_config": {
      "learning_rate": 0.004,
      "weight_decay": 0.1,
      "min_lr_ratio": 0,
      "warmup": 0,
      "momentum": 0.98,
      "beta1": 0.8,
      "beta2": 0.98,
      "epsilon": 1e-15,
      "muon_epsilon": 1e-05,
      "max_grad_norm": 2,
      "lr_schedule": "linear",
      "muon_to_adam_lr": 0.3,
      "decay": 1,
      "train_batch_size": 256
    },
    "approximate_best_config_list": [
      {
        "learning_rate": 0.004,
        "weight_decay": 0.1,
        "min_lr_ratio": 0,
        "warmup": 0,
        "momentum": 0.98,
        "beta1": 0.8,
        "beta2": 0.98,
        "epsilon": 1e-15,
        "muon_epsilon": 1e-05,
        "max_grad_norm": 2,
        "lr_schedule": "linear",
        "muon_to_adam_lr": 0.3,
        "decay": 1,
        "train_batch_size": 256
      }
    ]
  },
  "a2db3163683ae3b112f9d90a07f758af": {
    "min_num": 0,
    "min_loss": 2.897803783416748,
    "best_config": {
      "learning_rate": 0.004,
      "weight_decay": 0.1,
      "min_lr_ratio": 0,
      "warmup": 1000,
      "beta1": 0.95,
      "beta2": 0.99,
      "shampoo_beta": 0.9,
      "precondition_frequency": 10,
      "partition_grads_into_blocks": true,
      "block_size": 512,
      "epsilon": 1e-10,
      "max_grad_norm": 1,
      "train_batch_size": 256
    },
    "approximate_best_config_list": [
      {
        "learning_rate": 0.004,
        "weight_decay": 0.1,
        "min_lr_ratio": 0,
        "warmup": 1000,
        "beta1": 0.95,
        "beta2": 0.99,
        "shampoo_beta": 0.9,
        "precondition_frequency": 10,
        "partition_grads_into_blocks": true,
        "block_size": 512,
        "epsilon": 1e-10,
        "max_grad_norm": 1,
        "train_batch_size": 256
      }
    ]
  },
  "c18048ec5d36e11f59dd3f5f93517fb0": {
    "min_num": 0,
    "min_loss": 2.8293275833129883,
    "best_config": {
      "learning_rate": 0.004,
      "weight_decay": 0.1,
      "min_lr_ratio": 0,
      "warmup": 1000,
      "beta1": 0.95,
      "beta2": 0.99,
      "shampoo_beta": 0.9,
      "precondition_frequency": 10,
      "partition_grads_into_blocks": true,
      "block_size": 512,
      "epsilon": 1e-10,
      "max_grad_norm": 1,
      "train_batch_size": 256
    },
    "approximate_best_config_list": [
      {
        "learning_rate": 0.004,
        "weight_decay": 0.1,
        "min_lr_ratio": 0,
        "warmup": 1000,
        "beta1": 0.95,
        "beta2": 0.99,
        "shampoo_beta": 0.9,
        "precondition_frequency": 10,
        "partition_grads_into_blocks": true,
        "block_size": 512,
        "epsilon": 1e-10,
        "max_grad_norm": 1,
        "train_batch_size": 256
      }
    ]
  },
  "4aa861a057f650ac779754b07f34df14": {
    "min_num": 0,
    "min_loss": 2.782505750656128,
    "best_config": {
      "learning_rate": 0.004,
      "weight_decay": 0.1,
      "min_lr_ratio": 0,
      "warmup": 1000,
      "beta1": 0.95,
      "beta2": 0.99,
      "shampoo_beta": 0.9,
      "precondition_frequency": 10,
      "partition_grads_into_blocks": true,
      "block_size": 512,
      "epsilon": 1e-10,
      "max_grad_norm": 1,
      "train_batch_size": 256
    },
    "approximate_best_config_list": [
      {
        "learning_rate": 0.004,
        "weight_decay": 0.1,
        "min_lr_ratio": 0,
        "warmup": 1000,
        "beta1": 0.95,
        "beta2": 0.99,
        "shampoo_beta": 0.9,
        "precondition_frequency": 10,
        "partition_grads_into_blocks": true,
        "block_size": 512,
        "epsilon": 1e-10,
        "max_grad_norm": 1,
        "train_batch_size": 256
      }
    ]
  },
  "dc65a46bfe26703073c0d2de78ba0091": {
    "min_num": 0,
    "min_loss": 2.7485294342041016,
    "best_config": {
      "learning_rate": 0.004,
      "weight_decay": 0.1,
      "min_lr_ratio": 0,
      "warmup": 1000,
      "beta1": 0.95,
      "beta2": 0.99,
      "shampoo_beta": 0.9,
      "precondition_frequency": 10,
      "partition_grads_into_blocks": true,
      "block_size": 512,
      "epsilon": 1e-10,
      "max_grad_norm": 1,
      "train_batch_size": 256
    },
    "approximate_best_config_list": [
      {
        "learning_rate": 0.004,
        "weight_decay": 0.1,
        "min_lr_ratio": 0,
        "warmup": 1000,
        "beta1": 0.95,
        "beta2": 0.99,
        "shampoo_beta": 0.9,
        "precondition_frequency": 10,
        "partition_grads_into_blocks": true,
        "block_size": 512,
        "epsilon": 1e-10,
        "max_grad_norm": 1,
        "train_batch_size": 256
      }
    ]
  }
}