{
  "_runtime": 5943.127980243,
  "_step": 44100,
  "_timestamp": 1780153549.9719002,
  "_wandb.runtime": 335,
  "backend": "tpu",
  "eval/bpb": 1.139482855796814,
  "eval/loading_time": 0.3294627239702095,
  "eval/loss": 3.322139024734497,
  "eval/macro_bpb": 1.2166467905044556,
  "eval/macro_loss": 3.484081745147705,
  "eval/paloma/4chan/bpb": 1.279539704322815,
  "eval/paloma/4chan/loss": 2.9796009063720703,
  "eval/paloma/bpb": 1.146643042564392,
  "eval/paloma/c4_100_domains/bpb": 1.0547921657562256,
  "eval/paloma/c4_100_domains/loss": 3.3807876110076904,
  "eval/paloma/c4_en/bpb": 1.0753726959228516,
  "eval/paloma/c4_en/loss": 3.494075059890747,
  "eval/paloma/dolma-v1_5/bpb": 1.1115028858184814,
  "eval/paloma/dolma-v1_5/loss": 3.3162713050842285,
  "eval/paloma/dolma_100_programing_languages/bpb": 1.050619125366211,
  "eval/paloma/dolma_100_programing_languages/loss": 2.4196527004241943,
  "eval/paloma/dolma_100_subreddits/bpb": 1.2411240339279177,
  "eval/paloma/dolma_100_subreddits/loss": 3.779753446578979,
  "eval/paloma/falcon-refinedweb/bpb": 1.1489784717559814,
  "eval/paloma/falcon-refinedweb/loss": 3.600384473800659,
  "eval/paloma/gab/bpb": 1.9953546524047852,
  "eval/paloma/gab/loss": 4.8421173095703125,
  "eval/paloma/m2d2_s2orc_unsplit/bpb": 1.0989973545074463,
  "eval/paloma/m2d2_s2orc_unsplit/loss": 3.302337169647217,
  "eval/paloma/m2d2_wikipedia_unsplit/bpb": 1.053376317024231,
  "eval/paloma/m2d2_wikipedia_unsplit/loss": 3.255277633666992,
  "eval/paloma/macro_bpb": 1.2815388441085815,
  "eval/paloma/macro_loss": 3.562526226043701,
  "eval/paloma/manosphere_meta_sep/bpb": 1.2929999828338623,
  "eval/paloma/manosphere_meta_sep/loss": 3.7854409217834473,
  "eval/paloma/mc4/bpb": 1.0885692834854126,
  "eval/paloma/mc4/loss": 3.1445858478546143,
  "eval/paloma/micro_loss": 3.321924924850464,
  "eval/paloma/ptb/bpb": 1.2040414810180664,
  "eval/paloma/ptb/loss": 3.829164981842041,
  "eval/paloma/redpajama/bpb": 1.1625696420669556,
  "eval/paloma/redpajama/loss": 3.3105509281158447,
  "eval/paloma/twitterAAE_HELM_fixed/bpb": 2.571833372116089,
  "eval/paloma/twitterAAE_HELM_fixed/loss": 5.180118560791016,
  "eval/paloma/wikitext_103/bpb": 1.0749493837356567,
  "eval/paloma/wikitext_103/loss": 3.380303382873535,
  "eval/total_time": 76.93229803299982,
  "eval/uncheatable_eval/ao3_english/bpb": 1.2951874732971191,
  "eval/uncheatable_eval/ao3_english/loss": 3.930256128311157,
  "eval/uncheatable_eval/arxiv_computer_science/bpb": 0.9866601228713988,
  "eval/uncheatable_eval/arxiv_computer_science/loss": 3.5973618030548096,
  "eval/uncheatable_eval/arxiv_physics/bpb": 1.0799516439437866,
  "eval/uncheatable_eval/arxiv_physics/loss": 3.5505056381225586,
  "eval/uncheatable_eval/bbc_news/bpb": 1.0052047967910769,
  "eval/uncheatable_eval/bbc_news/loss": 3.303422212600708,
  "eval/uncheatable_eval/bpb": 1.0749149322509766,
  "eval/uncheatable_eval/github_cpp/bpb": 1.0230172872543335,
  "eval/uncheatable_eval/github_cpp/loss": 2.615971565246582,
  "eval/uncheatable_eval/github_python/bpb": 1.010647177696228,
  "eval/uncheatable_eval/github_python/loss": 2.919396162033081,
  "eval/uncheatable_eval/macro_bpb": 1.0683221817016602,
  "eval/uncheatable_eval/macro_loss": 3.304779291152954,
  "eval/uncheatable_eval/micro_loss": 3.324167013168335,
  "eval/uncheatable_eval/wikipedia_english/bpb": 1.0775867700576782,
  "eval/uncheatable_eval/wikipedia_english/loss": 3.216541290283203,
  "global_step": 44100,
  "grad/norm/embeddings.token_embeddings.weight": 0.03481511399149895,
  "grad/norm/lm_head.weight": 0.18801765143871307,
  "grad/norm/total": 0.3308027684688568,
  "grad/norm/transformer.layers.0.input_layernorm.weight": 0.002548050135374069,
  "grad/norm/transformer.layers.0.mlp.down_proj.weight": 0.04691290110349655,
  "grad/norm/transformer.layers.0.mlp.gate_proj.weight": 0.0092302355915308,
  "grad/norm/transformer.layers.0.mlp.up_proj.weight": 0.00873491819947958,
  "grad/norm/transformer.layers.0.post_attention_layernorm.weight": 0.002943791914731264,
  "grad/norm/transformer.layers.0.self_attn.k_norm.weight": 0.0006406842148862779,
  "grad/norm/transformer.layers.0.self_attn.k_proj.weight": 0.010689262300729752,
  "grad/norm/transformer.layers.0.self_attn.o_proj.weight": 0.04776625335216522,
  "grad/norm/transformer.layers.0.self_attn.q_norm.weight": 0.000665274157654494,
  "grad/norm/transformer.layers.0.self_attn.q_proj.weight": 0.00955493189394474,
  "grad/norm/transformer.layers.0.self_attn.v_proj.weight": 0.04485486447811127,
  "grad/norm/transformer.layers.1.input_layernorm.weight": 0.003595278365537524,
  "grad/norm/transformer.layers.1.mlp.down_proj.weight": 0.045675069093704224,
  "grad/norm/transformer.layers.1.mlp.gate_proj.weight": 0.01670428179204464,
  "grad/norm/transformer.layers.1.mlp.up_proj.weight": 0.016372526064515114,
  "grad/norm/transformer.layers.1.post_attention_layernorm.weight": 0.00222361134365201,
  "grad/norm/transformer.layers.1.self_attn.k_norm.weight": 0.0007193271885626018,
  "grad/norm/transformer.layers.1.self_attn.k_proj.weight": 0.00681672990322113,
  "grad/norm/transformer.layers.1.self_attn.o_proj.weight": 0.020036019384860992,
  "grad/norm/transformer.layers.1.self_attn.q_norm.weight": 0.0008211226668208838,
  "grad/norm/transformer.layers.1.self_attn.q_proj.weight": 0.007991881109774113,
  "grad/norm/transformer.layers.1.self_attn.v_proj.weight": 0.019703516736626625,
  "grad/norm/transformer.layers.10.input_layernorm.weight": 0.0016008276725187898,
  "grad/norm/transformer.layers.10.mlp.down_proj.weight": 0.042109403759241104,
  "grad/norm/transformer.layers.10.mlp.gate_proj.weight": 0.02041415311396122,
  "grad/norm/transformer.layers.10.mlp.up_proj.weight": 0.018068617209792137,
  "grad/norm/transformer.layers.10.post_attention_layernorm.weight": 0.0007653284701518714,
  "grad/norm/transformer.layers.10.self_attn.k_norm.weight": 0.0004475172318052501,
  "grad/norm/transformer.layers.10.self_attn.k_proj.weight": 0.008577867411077023,
  "grad/norm/transformer.layers.10.self_attn.o_proj.weight": 0.011501080356538296,
  "grad/norm/transformer.layers.10.self_attn.q_norm.weight": 0.00043040435411967337,
  "grad/norm/transformer.layers.10.self_attn.q_proj.weight": 0.008201397024095058,
  "grad/norm/transformer.layers.10.self_attn.v_proj.weight": 0.011849031783640385,
  "grad/norm/transformer.layers.11.input_layernorm.weight": 0.0015211306745186448,
  "grad/norm/transformer.layers.11.mlp.down_proj.weight": 0.04307013377547264,
  "grad/norm/transformer.layers.11.mlp.gate_proj.weight": 0.020030658692121502,
  "grad/norm/transformer.layers.11.mlp.up_proj.weight": 0.01755204237997532,
  "grad/norm/transformer.layers.11.post_attention_layernorm.weight": 0.0006574565777555108,
  "grad/norm/transformer.layers.11.self_attn.k_norm.weight": 0.0004788583901245147,
  "grad/norm/transformer.layers.11.self_attn.k_proj.weight": 0.011011914350092413,
  "grad/norm/transformer.layers.11.self_attn.o_proj.weight": 0.01513406913727522,
  "grad/norm/transformer.layers.11.self_attn.q_norm.weight": 0.0004962416714988649,
  "grad/norm/transformer.layers.11.self_attn.q_proj.weight": 0.01095186173915863,
  "grad/norm/transformer.layers.11.self_attn.v_proj.weight": 0.015022248029708862,
  "grad/norm/transformer.layers.12.input_layernorm.weight": 0.0011635508853942156,
  "grad/norm/transformer.layers.12.mlp.down_proj.weight": 0.045061033219099045,
  "grad/norm/transformer.layers.12.mlp.gate_proj.weight": 0.020560123026371,
  "grad/norm/transformer.layers.12.mlp.up_proj.weight": 0.01827719621360302,
  "grad/norm/transformer.layers.12.post_attention_layernorm.weight": 0.0005927359452471137,
  "grad/norm/transformer.layers.12.self_attn.k_norm.weight": 0.0005417272332124412,
  "grad/norm/transformer.layers.12.self_attn.k_proj.weight": 0.008625226095318794,
  "grad/norm/transformer.layers.12.self_attn.o_proj.weight": 0.01154736801981926,
  "grad/norm/transformer.layers.12.self_attn.q_norm.weight": 0.0005493923090398312,
  "grad/norm/transformer.layers.12.self_attn.q_proj.weight": 0.008463751524686813,
  "grad/norm/transformer.layers.12.self_attn.v_proj.weight": 0.01076889131218195,
  "grad/norm/transformer.layers.13.input_layernorm.weight": 0.0011333405273035169,
  "grad/norm/transformer.layers.13.mlp.down_proj.weight": 0.04720509797334671,
  "grad/norm/transformer.layers.13.mlp.gate_proj.weight": 0.022018913179636,
  "grad/norm/transformer.layers.13.mlp.up_proj.weight": 0.019422277808189392,
  "grad/norm/transformer.layers.13.post_attention_layernorm.weight": 0.0011224182089790702,
  "grad/norm/transformer.layers.13.self_attn.k_norm.weight": 0.00047121456009335816,
  "grad/norm/transformer.layers.13.self_attn.k_proj.weight": 0.007742523215711117,
  "grad/norm/transformer.layers.13.self_attn.o_proj.weight": 0.010318229906260967,
  "grad/norm/transformer.layers.13.self_attn.q_norm.weight": 0.0004688092158176005,
  "grad/norm/transformer.layers.13.self_attn.q_proj.weight": 0.007403216324746609,
  "grad/norm/transformer.layers.13.self_attn.v_proj.weight": 0.009991969913244247,
  "grad/norm/transformer.layers.14.input_layernorm.weight": 0.002397847594693303,
  "grad/norm/transformer.layers.14.mlp.down_proj.weight": 0.07257378101348877,
  "grad/norm/transformer.layers.14.mlp.gate_proj.weight": 0.032942160964012146,
  "grad/norm/transformer.layers.14.mlp.up_proj.weight": 0.031913064420223236,
  "grad/norm/transformer.layers.14.post_attention_layernorm.weight": 0.007049460429698229,
  "grad/norm/transformer.layers.14.self_attn.k_norm.weight": 0.00034429263905622065,
  "grad/norm/transformer.layers.14.self_attn.k_proj.weight": 0.004499631933867931,
  "grad/norm/transformer.layers.14.self_attn.o_proj.weight": 0.00869541522115469,
  "grad/norm/transformer.layers.14.self_attn.q_norm.weight": 0.0003445397596806288,
  "grad/norm/transformer.layers.14.self_attn.q_proj.weight": 0.004863015841692686,
  "grad/norm/transformer.layers.14.self_attn.v_proj.weight": 0.012295281514525414,
  "grad/norm/transformer.layers.2.input_layernorm.weight": 0.0027511930093169212,
  "grad/norm/transformer.layers.2.mlp.down_proj.weight": 0.1097077950835228,
  "grad/norm/transformer.layers.2.mlp.gate_proj.weight": 0.019666729494929314,
  "grad/norm/transformer.layers.2.mlp.up_proj.weight": 0.01835564337670803,
  "grad/norm/transformer.layers.2.post_attention_layernorm.weight": 0.001795310527086258,
  "grad/norm/transformer.layers.2.self_attn.k_norm.weight": 0.0004817243607249111,
  "grad/norm/transformer.layers.2.self_attn.k_proj.weight": 0.008184955455362797,
  "grad/norm/transformer.layers.2.self_attn.o_proj.weight": 0.02000000886619091,
  "grad/norm/transformer.layers.2.self_attn.q_norm.weight": 0.0004823390045203269,
  "grad/norm/transformer.layers.2.self_attn.q_proj.weight": 0.008925637230277061,
  "grad/norm/transformer.layers.2.self_attn.v_proj.weight": 0.022793596610426903,
  "grad/norm/transformer.layers.3.input_layernorm.weight": 0.001547708408907056,
  "grad/norm/transformer.layers.3.mlp.down_proj.weight": 0.04968241602182388,
  "grad/norm/transformer.layers.3.mlp.gate_proj.weight": 0.020254572853446007,
  "grad/norm/transformer.layers.3.mlp.up_proj.weight": 0.01838192529976368,
  "grad/norm/transformer.layers.3.post_attention_layernorm.weight": 0.002526242518797517,
  "grad/norm/transformer.layers.3.self_attn.k_norm.weight": 0.0010138378711417315,
  "grad/norm/transformer.layers.3.self_attn.k_proj.weight": 0.014935734681785108,
  "grad/norm/transformer.layers.3.self_attn.o_proj.weight": 0.019009431824088097,
  "grad/norm/transformer.layers.3.self_attn.q_norm.weight": 0.0007789134979248047,
  "grad/norm/transformer.layers.3.self_attn.q_proj.weight": 0.013914216309785845,
  "grad/norm/transformer.layers.3.self_attn.v_proj.weight": 0.02489776909351349,
  "grad/norm/transformer.layers.4.input_layernorm.weight": 0.00175605493132025,
  "grad/norm/transformer.layers.4.mlp.down_proj.weight": 0.04483462497591973,
  "grad/norm/transformer.layers.4.mlp.gate_proj.weight": 0.02070816233754158,
  "grad/norm/transformer.layers.4.mlp.up_proj.weight": 0.018725203350186348,
  "grad/norm/transformer.layers.4.post_attention_layernorm.weight": 0.002160667674615979,
  "grad/norm/transformer.layers.4.self_attn.k_norm.weight": 0.0009409068152308464,
  "grad/norm/transformer.layers.4.self_attn.k_proj.weight": 0.01745270937681198,
  "grad/norm/transformer.layers.4.self_attn.o_proj.weight": 0.02023405395448208,
  "grad/norm/transformer.layers.4.self_attn.q_norm.weight": 0.000880134932231158,
  "grad/norm/transformer.layers.4.self_attn.q_proj.weight": 0.015379694290459156,
  "grad/norm/transformer.layers.4.self_attn.v_proj.weight": 0.02476663701236248,
  "grad/norm/transformer.layers.5.input_layernorm.weight": 0.001073775114491582,
  "grad/norm/transformer.layers.5.mlp.down_proj.weight": 0.0447709821164608,
  "grad/norm/transformer.layers.5.mlp.gate_proj.weight": 0.02121123857796192,
  "grad/norm/transformer.layers.5.mlp.up_proj.weight": 0.0197552852332592,
  "grad/norm/transformer.layers.5.post_attention_layernorm.weight": 0.0012036162661388516,
  "grad/norm/transformer.layers.5.self_attn.k_norm.weight": 0.0007827894878573716,
  "grad/norm/transformer.layers.5.self_attn.k_proj.weight": 0.014779997058212755,
  "grad/norm/transformer.layers.5.self_attn.o_proj.weight": 0.019426103681325912,
  "grad/norm/transformer.layers.5.self_attn.q_norm.weight": 0.0007747363997623324,
  "grad/norm/transformer.layers.5.self_attn.q_proj.weight": 0.0144747169688344,
  "grad/norm/transformer.layers.5.self_attn.v_proj.weight": 0.0223503690212965,
  "grad/norm/transformer.layers.6.input_layernorm.weight": 0.0014165531611070037,
  "grad/norm/transformer.layers.6.mlp.down_proj.weight": 0.04452229663729668,
  "grad/norm/transformer.layers.6.mlp.gate_proj.weight": 0.02112724259495735,
  "grad/norm/transformer.layers.6.mlp.up_proj.weight": 0.019867360591888428,
  "grad/norm/transformer.layers.6.post_attention_layernorm.weight": 0.0009470165241509676,
  "grad/norm/transformer.layers.6.self_attn.k_norm.weight": 0.0009095294517464936,
  "grad/norm/transformer.layers.6.self_attn.k_proj.weight": 0.01226656325161457,
  "grad/norm/transformer.layers.6.self_attn.o_proj.weight": 0.01822003163397312,
  "grad/norm/transformer.layers.6.self_attn.q_norm.weight": 0.0008739030454307795,
  "grad/norm/transformer.layers.6.self_attn.q_proj.weight": 0.012188098393380642,
  "grad/norm/transformer.layers.6.self_attn.v_proj.weight": 0.02097698301076889,
  "grad/norm/transformer.layers.7.input_layernorm.weight": 0.0011931981425732374,
  "grad/norm/transformer.layers.7.mlp.down_proj.weight": 0.04283412918448448,
  "grad/norm/transformer.layers.7.mlp.gate_proj.weight": 0.02004317007958889,
  "grad/norm/transformer.layers.7.mlp.up_proj.weight": 0.018794162198901176,
  "grad/norm/transformer.layers.7.post_attention_layernorm.weight": 0.0009868721244856715,
  "grad/norm/transformer.layers.7.self_attn.k_norm.weight": 0.001030400046147406,
  "grad/norm/transformer.layers.7.self_attn.k_proj.weight": 0.013020731508731842,
  "grad/norm/transformer.layers.7.self_attn.o_proj.weight": 0.019262386485934258,
  "grad/norm/transformer.layers.7.self_attn.q_norm.weight": 0.0010012320708483458,
  "grad/norm/transformer.layers.7.self_attn.q_proj.weight": 0.013377144001424313,
  "grad/norm/transformer.layers.7.self_attn.v_proj.weight": 0.02249709889292717,
  "grad/norm/transformer.layers.8.input_layernorm.weight": 0.001442262320779264,
  "grad/norm/transformer.layers.8.mlp.down_proj.weight": 0.042584098875522614,
  "grad/norm/transformer.layers.8.mlp.gate_proj.weight": 0.020011456683278084,
  "grad/norm/transformer.layers.8.mlp.up_proj.weight": 0.018156567588448524,
  "grad/norm/transformer.layers.8.post_attention_layernorm.weight": 0.0010178060038015246,
  "grad/norm/transformer.layers.8.self_attn.k_norm.weight": 0.0007120163645595312,
  "grad/norm/transformer.layers.8.self_attn.k_proj.weight": 0.017929669469594955,
  "grad/norm/transformer.layers.8.self_attn.o_proj.weight": 0.017777398228645325,
  "grad/norm/transformer.layers.8.self_attn.q_norm.weight": 0.000704722129739821,
  "grad/norm/transformer.layers.8.self_attn.q_proj.weight": 0.016803331673145294,
  "grad/norm/transformer.layers.8.self_attn.v_proj.weight": 0.020067980512976646,
  "grad/norm/transformer.layers.9.input_layernorm.weight": 0.0007832773262634873,
  "grad/norm/transformer.layers.9.mlp.down_proj.weight": 0.04249485582113266,
  "grad/norm/transformer.layers.9.mlp.gate_proj.weight": 0.02014375664293766,
  "grad/norm/transformer.layers.9.mlp.up_proj.weight": 0.01773984543979168,
  "grad/norm/transformer.layers.9.post_attention_layernorm.weight": 0.0007710622739978135,
  "grad/norm/transformer.layers.9.self_attn.k_norm.weight": 0.0009321160614490508,
  "grad/norm/transformer.layers.9.self_attn.k_proj.weight": 0.010697613470256329,
  "grad/norm/transformer.layers.9.self_attn.o_proj.weight": 0.015446605160832403,
  "grad/norm/transformer.layers.9.self_attn.q_norm.weight": 0.0008805660181678832,
  "grad/norm/transformer.layers.9.self_attn.q_proj.weight": 0.01061700377613306,
  "grad/norm/transformer.layers.9.self_attn.v_proj.weight": 0.016560303047299385,
  "grad/norm/transformer.norm.weight": 0.010422422550618649,
  "num_devices": 8,
  "num_hosts": 1,
  "optim/adam_lr": 0.00027285260148346424,
  "optim/learning_rate": 0.002820610301569104,
  "parameter_count": 837007744,
  "params/norm/embeddings.token_embeddings.weight": 577.2222900390625,
  "params/norm/lm_head.weight": 353.4337463378906,
  "params/norm/total": 884.0320434570312,
  "params/norm/transformer.layers.0.input_layernorm.weight": 27.474918365478516,
  "params/norm/transformer.layers.0.mlp.down_proj.weight": 37.04581832885742,
  "params/norm/transformer.layers.0.mlp.gate_proj.weight": 74.06124114990234,
  "params/norm/transformer.layers.0.mlp.up_proj.weight": 74.06292724609375,
  "params/norm/transformer.layers.0.post_attention_layernorm.weight": 15.323168754577637,
  "params/norm/transformer.layers.0.self_attn.k_norm.weight": 15.147650718688965,
  "params/norm/transformer.layers.0.self_attn.k_proj.weight": 37.04163360595703,
  "params/norm/transformer.layers.0.self_attn.o_proj.weight": 37.04147720336914,
  "params/norm/transformer.layers.0.self_attn.q_norm.weight": 15.132035255432127,
  "params/norm/transformer.layers.0.self_attn.q_proj.weight": 37.04303359985352,
  "params/norm/transformer.layers.0.self_attn.v_proj.weight": 37.0211296081543,
  "params/norm/transformer.layers.1.input_layernorm.weight": 14.145662307739258,
  "params/norm/transformer.layers.1.mlp.down_proj.weight": 37.02233123779297,
  "params/norm/transformer.layers.1.mlp.gate_proj.weight": 74.06169891357422,
  "params/norm/transformer.layers.1.mlp.up_proj.weight": 74.06851959228516,
  "params/norm/transformer.layers.1.post_attention_layernorm.weight": 28.532548904418945,
  "params/norm/transformer.layers.1.self_attn.k_norm.weight": 13.909353256225586,
  "params/norm/transformer.layers.1.self_attn.k_proj.weight": 37.0546760559082,
  "params/norm/transformer.layers.1.self_attn.o_proj.weight": 37.03497695922851,
  "params/norm/transformer.layers.1.self_attn.q_norm.weight": 13.913674354553224,
  "params/norm/transformer.layers.1.self_attn.q_proj.weight": 37.01294708251953,
  "params/norm/transformer.layers.1.self_attn.v_proj.weight": 37.040382385253906,
  "params/norm/transformer.layers.10.input_layernorm.weight": 39.27304458618164,
  "params/norm/transformer.layers.10.mlp.down_proj.weight": 37.03290557861328,
  "params/norm/transformer.layers.10.mlp.gate_proj.weight": 74.02606964111328,
  "params/norm/transformer.layers.10.mlp.up_proj.weight": 74.0457992553711,
  "params/norm/transformer.layers.10.post_attention_layernorm.weight": 48.09608459472656,
  "params/norm/transformer.layers.10.self_attn.k_norm.weight": 15.180825233459473,
  "params/norm/transformer.layers.10.self_attn.k_proj.weight": 37.03494644165039,
  "params/norm/transformer.layers.10.self_attn.o_proj.weight": 36.9937744140625,
  "params/norm/transformer.layers.10.self_attn.q_norm.weight": 15.354575157165527,
  "params/norm/transformer.layers.10.self_attn.q_proj.weight": 37.067901611328125,
  "params/norm/transformer.layers.10.self_attn.v_proj.weight": 37.014129638671875,
  "params/norm/transformer.layers.11.input_layernorm.weight": 48.37541961669922,
  "params/norm/transformer.layers.11.mlp.down_proj.weight": 37.03205871582031,
  "params/norm/transformer.layers.11.mlp.gate_proj.weight": 74.04916381835938,
  "params/norm/transformer.layers.11.mlp.up_proj.weight": 74.04060363769531,
  "params/norm/transformer.layers.11.post_attention_layernorm.weight": 49.86933898925781,
  "params/norm/transformer.layers.11.self_attn.k_norm.weight": 16.591144561767578,
  "params/norm/transformer.layers.11.self_attn.k_proj.weight": 37.05302810668945,
  "params/norm/transformer.layers.11.self_attn.o_proj.weight": 37.01345443725586,
  "params/norm/transformer.layers.11.self_attn.q_norm.weight": 16.748455047607422,
  "params/norm/transformer.layers.11.self_attn.q_proj.weight": 37.02569961547851,
  "params/norm/transformer.layers.11.self_attn.v_proj.weight": 37.029518127441406,
  "params/norm/transformer.layers.12.input_layernorm.weight": 40.38436508178711,
  "params/norm/transformer.layers.12.mlp.down_proj.weight": 37.01676177978515,
  "params/norm/transformer.layers.12.mlp.gate_proj.weight": 74.08039093017578,
  "params/norm/transformer.layers.12.mlp.up_proj.weight": 74.1028060913086,
  "params/norm/transformer.layers.12.post_attention_layernorm.weight": 52.54986953735352,
  "params/norm/transformer.layers.12.self_attn.k_norm.weight": 15.2623929977417,
  "params/norm/transformer.layers.12.self_attn.k_proj.weight": 37.01127243041992,
  "params/norm/transformer.layers.12.self_attn.o_proj.weight": 37.03204345703125,
  "params/norm/transformer.layers.12.self_attn.q_norm.weight": 15.398513793945312,
  "params/norm/transformer.layers.12.self_attn.q_proj.weight": 37.05075454711914,
  "params/norm/transformer.layers.12.self_attn.v_proj.weight": 37.02139663696289,
  "params/norm/transformer.layers.13.input_layernorm.weight": 37.30472183227539,
  "params/norm/transformer.layers.13.mlp.down_proj.weight": 37.04045867919922,
  "params/norm/transformer.layers.13.mlp.gate_proj.weight": 74.06774139404297,
  "params/norm/transformer.layers.13.mlp.up_proj.weight": 74.08116912841797,
  "params/norm/transformer.layers.13.post_attention_layernorm.weight": 54.1159782409668,
  "params/norm/transformer.layers.13.self_attn.k_norm.weight": 14.748899459838867,
  "params/norm/transformer.layers.13.self_attn.k_proj.weight": 37.02127456665039,
  "params/norm/transformer.layers.13.self_attn.o_proj.weight": 37.04453659057617,
  "params/norm/transformer.layers.13.self_attn.q_norm.weight": 14.840746879577637,
  "params/norm/transformer.layers.13.self_attn.q_proj.weight": 37.01716232299805,
  "params/norm/transformer.layers.13.self_attn.v_proj.weight": 37.01156997680664,
  "params/norm/transformer.layers.14.input_layernorm.weight": 30.122737884521484,
  "params/norm/transformer.layers.14.mlp.down_proj.weight": 37.038448333740234,
  "params/norm/transformer.layers.14.mlp.gate_proj.weight": 74.0669174194336,
  "params/norm/transformer.layers.14.mlp.up_proj.weight": 74.0125503540039,
  "params/norm/transformer.layers.14.post_attention_layernorm.weight": 51.005615234375,
  "params/norm/transformer.layers.14.self_attn.k_norm.weight": 14.508474349975586,
  "params/norm/transformer.layers.14.self_attn.k_proj.weight": 37.01286697387695,
  "params/norm/transformer.layers.14.self_attn.o_proj.weight": 37.05402755737305,
  "params/norm/transformer.layers.14.self_attn.q_norm.weight": 14.572088241577148,
  "params/norm/transformer.layers.14.self_attn.q_proj.weight": 36.9988899230957,
  "params/norm/transformer.layers.14.self_attn.v_proj.weight": 37.02604675292969,
  "params/norm/transformer.layers.2.input_layernorm.weight": 20.048973083496097,
  "params/norm/transformer.layers.2.mlp.down_proj.weight": 37.02853012084961,
  "params/norm/transformer.layers.2.mlp.gate_proj.weight": 74.07322692871094,
  "params/norm/transformer.layers.2.mlp.up_proj.weight": 74.0982666015625,
  "params/norm/transformer.layers.2.post_attention_layernorm.weight": 33.29817199707031,
  "params/norm/transformer.layers.2.self_attn.k_norm.weight": 14.521240234375,
  "params/norm/transformer.layers.2.self_attn.k_proj.weight": 37.03982925415039,
  "params/norm/transformer.layers.2.self_attn.o_proj.weight": 37.04299545288086,
  "params/norm/transformer.layers.2.self_attn.q_norm.weight": 14.538259506225586,
  "params/norm/transformer.layers.2.self_attn.q_proj.weight": 37.02337646484375,
  "params/norm/transformer.layers.2.self_attn.v_proj.weight": 37.01971435546875,
  "params/norm/transformer.layers.3.input_layernorm.weight": 27.688047409057617,
  "params/norm/transformer.layers.3.mlp.down_proj.weight": 37.030147552490234,
  "params/norm/transformer.layers.3.mlp.gate_proj.weight": 74.04695892333984,
  "params/norm/transformer.layers.3.mlp.up_proj.weight": 74.04467010498047,
  "params/norm/transformer.layers.3.post_attention_layernorm.weight": 35.1819953918457,
  "params/norm/transformer.layers.3.self_attn.k_norm.weight": 15.640026092529297,
  "params/norm/transformer.layers.3.self_attn.k_proj.weight": 37.01539993286133,
  "params/norm/transformer.layers.3.self_attn.o_proj.weight": 37.012245178222656,
  "params/norm/transformer.layers.3.self_attn.q_norm.weight": 15.703079223632812,
  "params/norm/transformer.layers.3.self_attn.q_proj.weight": 37.03612518310547,
  "params/norm/transformer.layers.3.self_attn.v_proj.weight": 37.02339553833008,
  "params/norm/transformer.layers.4.input_layernorm.weight": 36.55474090576172,
  "params/norm/transformer.layers.4.mlp.down_proj.weight": 37.02961349487305,
  "params/norm/transformer.layers.4.mlp.gate_proj.weight": 74.02041625976562,
  "params/norm/transformer.layers.4.mlp.up_proj.weight": 74.07942962646484,
  "params/norm/transformer.layers.4.post_attention_layernorm.weight": 36.86787796020508,
  "params/norm/transformer.layers.4.self_attn.k_norm.weight": 15.490619659423828,
  "params/norm/transformer.layers.4.self_attn.k_proj.weight": 37.00847625732422,
  "params/norm/transformer.layers.4.self_attn.o_proj.weight": 37.03116607666016,
  "params/norm/transformer.layers.4.self_attn.q_norm.weight": 15.55311107635498,
  "params/norm/transformer.layers.4.self_attn.q_proj.weight": 37.020938873291016,
  "params/norm/transformer.layers.4.self_attn.v_proj.weight": 37.08905792236328,
  "params/norm/transformer.layers.5.input_layernorm.weight": 36.19023513793945,
  "params/norm/transformer.layers.5.mlp.down_proj.weight": 37.02603912353515,
  "params/norm/transformer.layers.5.mlp.gate_proj.weight": 74.05500030517578,
  "params/norm/transformer.layers.5.mlp.up_proj.weight": 74.06591033935547,
  "params/norm/transformer.layers.5.post_attention_layernorm.weight": 38.177711486816406,
  "params/norm/transformer.layers.5.self_attn.k_norm.weight": 16.585269927978516,
  "params/norm/transformer.layers.5.self_attn.k_proj.weight": 37.03839492797851,
  "params/norm/transformer.layers.5.self_attn.o_proj.weight": 36.99106979370117,
  "params/norm/transformer.layers.5.self_attn.q_norm.weight": 16.639034271240234,
  "params/norm/transformer.layers.5.self_attn.q_proj.weight": 37.01264953613281,
  "params/norm/transformer.layers.5.self_attn.v_proj.weight": 37.00463104248047,
  "params/norm/transformer.layers.6.input_layernorm.weight": 37.458885192871094,
  "params/norm/transformer.layers.6.mlp.down_proj.weight": 37.03972244262695,
  "params/norm/transformer.layers.6.mlp.gate_proj.weight": 74.03938293457031,
  "params/norm/transformer.layers.6.mlp.up_proj.weight": 74.050048828125,
  "params/norm/transformer.layers.6.post_attention_layernorm.weight": 38.63372039794922,
  "params/norm/transformer.layers.6.self_attn.k_norm.weight": 15.697689056396484,
  "params/norm/transformer.layers.6.self_attn.k_proj.weight": 37.0516471862793,
  "params/norm/transformer.layers.6.self_attn.o_proj.weight": 37.02827453613281,
  "params/norm/transformer.layers.6.self_attn.q_norm.weight": 15.77673625946045,
  "params/norm/transformer.layers.6.self_attn.q_proj.weight": 37.00654220581055,
  "params/norm/transformer.layers.6.self_attn.v_proj.weight": 37.02587890625,
  "params/norm/transformer.layers.7.input_layernorm.weight": 41.93030548095703,
  "params/norm/transformer.layers.7.mlp.down_proj.weight": 37.028446197509766,
  "params/norm/transformer.layers.7.mlp.gate_proj.weight": 74.01688385009766,
  "params/norm/transformer.layers.7.mlp.up_proj.weight": 74.06262969970703,
  "params/norm/transformer.layers.7.post_attention_layernorm.weight": 39.52946853637695,
  "params/norm/transformer.layers.7.self_attn.k_norm.weight": 16.825349807739258,
  "params/norm/transformer.layers.7.self_attn.k_proj.weight": 37.02914810180664,
  "params/norm/transformer.layers.7.self_attn.o_proj.weight": 37.01423645019531,
  "params/norm/transformer.layers.7.self_attn.q_norm.weight": 16.857534408569336,
  "params/norm/transformer.layers.7.self_attn.q_proj.weight": 37.01322937011719,
  "params/norm/transformer.layers.7.self_attn.v_proj.weight": 37.03545379638672,
  "params/norm/transformer.layers.8.input_layernorm.weight": 47.7228889465332,
  "params/norm/transformer.layers.8.mlp.down_proj.weight": 37.02062225341797,
  "params/norm/transformer.layers.8.mlp.gate_proj.weight": 74.06544494628906,
  "params/norm/transformer.layers.8.mlp.up_proj.weight": 74.06180572509766,
  "params/norm/transformer.layers.8.post_attention_layernorm.weight": 42.53768157958984,
  "params/norm/transformer.layers.8.self_attn.k_norm.weight": 17.527463912963867,
  "params/norm/transformer.layers.8.self_attn.k_proj.weight": 37.035186767578125,
  "params/norm/transformer.layers.8.self_attn.o_proj.weight": 37.004268646240234,
  "params/norm/transformer.layers.8.self_attn.q_norm.weight": 17.671628952026367,
  "params/norm/transformer.layers.8.self_attn.q_proj.weight": 37.03834533691406,
  "params/norm/transformer.layers.8.self_attn.v_proj.weight": 37.04667663574219,
  "params/norm/transformer.layers.9.input_layernorm.weight": 41.44325637817383,
  "params/norm/transformer.layers.9.mlp.down_proj.weight": 37.02263641357422,
  "params/norm/transformer.layers.9.mlp.gate_proj.weight": 74.08533477783203,
  "params/norm/transformer.layers.9.mlp.up_proj.weight": 74.05897521972656,
  "params/norm/transformer.layers.9.post_attention_layernorm.weight": 45.47585678100586,
  "params/norm/transformer.layers.9.self_attn.k_norm.weight": 15.957266807556152,
  "params/norm/transformer.layers.9.self_attn.k_proj.weight": 37.051536560058594,
  "params/norm/transformer.layers.9.self_attn.o_proj.weight": 37.07484436035156,
  "params/norm/transformer.layers.9.self_attn.q_norm.weight": 16.033716201782227,
  "params/norm/transformer.layers.9.self_attn.q_proj.weight": 37.010215759277344,
  "params/norm/transformer.layers.9.self_attn.v_proj.weight": 37.01481628417969,
  "params/norm/transformer.norm.weight": 52.17733001708984,
  "run_progress": 0.8,
  "throughput/device_kind": "TPU v6 lite",
  "throughput/duration": 0.2605727179998212,
  "throughput/examples_per_second": 61.40320492036691,
  "throughput/flops_per_example": 20408023646208,
  "throughput/gflops_per_second": 1253118.0579678034,
  "throughput/hook_time": 0.020994500000597327,
  "throughput/loading_time": 0.001009429999612621,
  "throughput/mean_mfu": 17.16510406982891,
  "throughput/mfu": 17.063154384093185,
  "throughput/mfu_sample_count": 500,
  "throughput/p10_mfu": 17.088983217708282,
  "throughput/p50_mfu": 17.315990291502672,
  "throughput/p90_mfu": 17.377098883744406,
  "throughput/stddev_mfu": 1.1161096958289587,
  "throughput/theoretical_flops": 7344000000000000,
  "throughput/theoretical_flops_per_device": 918000000000000,
  "throughput/tokens_per_second": 251507.5273538229,
  "throughput/total_gflops": 14400228013.142704,
  "throughput/total_tokens": 2890203136,
  "train/loss": 3.4986748695373535
}
