{
  "model_id": "cbs_lrq74_s5",
  "formula": "P(w)+E(w)+A(w)((N/N0)^(-alpha)-1)+B(w)((D/D0)^(-beta)-1)+C(w)((N/N0)^(-gamma)(D/D0)^(-delta)-1)",
  "anchor_kind": "lrq_scarcity",
  "anchor_description": "frozen GRP donor features plus two-phase low-rank high/HQ, low, synthetic, curated-technical sqrt masses and family sqrt shares",
  "barrier": {
    "strength": 5.0,
    "thresholds": {
      "phase0_reasoning_gate": 0.12,
      "phase1_tech_max": 0.55,
      "phase1_broad_min": 0.45,
      "max_domain_weight": 0.45
    },
    "formula": "strength * relu(p0_reasoning-0.12)^2 * (relu(p1_tech-0.55)^2 + relu(0.45-p1_broad)^2 + relu(max_domain-0.45)^2)"
  },
  "N0": 201149184.0,
  "D0": 5999951872.0,
  "exponents": {
    "alpha": 0.2,
    "beta": 0.25,
    "gamma": 0.3,
    "delta": 0.65
  },
  "head_A": "constant",
  "head_B": "family",
  "head_C": "constant",
  "pair_weight": 6.0,
  "ridge_anchor": 0.0001,
  "ridge_scale": 1e-05,
  "anchor_feature_count_including_intercept": 47,
  "scale_param_count": 9,
  "fitted_param_count_counting_exponents": 60,
  "total_constant_count_including_donor_and_barrier_constants": 74,
  "scale_coefficients_nonnegative": true,
  "scale_fit_success": true,
  "scale_fit_cost": 0.27062025194307143,
  "pair_count": 58,
  "anchor_features": [
    "broad_text:phase0_share",
    "broad_text:phase1_share",
    "broad_text:phase_delta",
    "broad_text:sqrt_phase1_share",
    "broad_text:total_signal_power",
    "broad_text:phase0_signal_power",
    "broad_text:phase1_signal_power",
    "broad_text:ceiling_penalty",
    "broad_text:phase0_entropy",
    "broad_text:phase1_entropy",
    "tech_code:phase0_share",
    "tech_code:phase1_share",
    "tech_code:phase_delta",
    "tech_code:sqrt_phase1_share",
    "tech_code:total_signal_power",
    "tech_code:phase0_signal_power",
    "tech_code:phase1_signal_power",
    "tech_code:ceiling_penalty",
    "tech_code:phase0_entropy",
    "tech_code:phase1_entropy",
    "reasoning:phase0_share",
    "reasoning:phase1_share",
    "reasoning:phase_delta",
    "reasoning:sqrt_phase1_share",
    "reasoning:total_signal_power",
    "reasoning:phase0_signal_power",
    "reasoning:phase1_signal_power",
    "reasoning:ceiling_penalty",
    "reasoning:phase0_entropy",
    "reasoning:phase1_entropy",
    "global:phase0_entropy",
    "global:phase1_entropy",
    "p0:high_or_hq:sqrt_mass",
    "p0:low_quality:sqrt_mass",
    "p0:synthetic:sqrt_mass",
    "p0:curated_technical:sqrt_mass",
    "p1:high_or_hq:sqrt_mass",
    "p1:low_quality:sqrt_mass",
    "p1:synthetic:sqrt_mass",
    "p1:curated_technical:sqrt_mass",
    "sqrt_p0_broad_text",
    "sqrt_p0_tech_code",
    "sqrt_p0_reasoning",
    "sqrt_p1_broad_text",
    "sqrt_p1_tech_code",
    "sqrt_p1_reasoning"
  ],
  "scale_head_features_A": [
    "A:0"
  ],
  "scale_head_features_B": [
    "B:0",
    "B:1",
    "B:2",
    "B:3",
    "B:4",
    "B:5",
    "B:6"
  ],
  "scale_head_features_C": [
    "C:0"
  ],
  "domain_names": [
    "dolma3_cc/art_and_design_high",
    "dolma3_cc/art_and_design_low",
    "dolma3_cc/crime_and_law_high",
    "dolma3_cc/crime_and_law_low",
    "dolma3_cc/education_and_jobs_high",
    "dolma3_cc/education_and_jobs_low",
    "dolma3_cc/electronics_and_hardware_high",
    "dolma3_cc/electronics_and_hardware_low",
    "dolma3_cc/entertainment_high",
    "dolma3_cc/entertainment_low",
    "dolma3_cc/finance_and_business_high",
    "dolma3_cc/finance_and_business_low",
    "dolma3_cc/food_and_dining_high",
    "dolma3_cc/food_and_dining_low",
    "dolma3_cc/games_high",
    "dolma3_cc/games_low",
    "dolma3_cc/health_high",
    "dolma3_cc/health_low",
    "dolma3_cc/history_and_geography_high",
    "dolma3_cc/history_and_geography_low",
    "dolma3_cc/industrial_high",
    "dolma3_cc/industrial_low",
    "dolma3_cc/literature_high",
    "dolma3_cc/literature_low",
    "dolma3_cc/science_math_and_technology_high",
    "dolma3_cc/science_math_and_technology_low",
    "dolma3_stack_edu",
    "dolma3_arxiv",
    "dolma3_finemath_3plus",
    "dolma3_wikipedia",
    "dolmino_common_crawl_hq",
    "dolmino_olmocr_pdfs_hq",
    "dolmino_stack_edu_fim",
    "dolmino_stem_heavy_crawl",
    "dolmino_synth_code",
    "dolmino_synth_instruction",
    "dolmino_synth_math",
    "dolmino_synth_qa",
    "dolmino_synth_thinking"
  ],
  "family_names": [
    "broad_text",
    "tech_code",
    "reasoning"
  ]
}
